gehseeker/__init__.py
gehseeker/gehseeker.2.0.0.cpython-311-windows.pyd
gehseeker/gehseeker.dll
gehseeker/gehseeker.py
gehseeker/highs.dll
gehseeker/libboost_filesystem-mt.dll
gehseeker/libstdc++-6.dll
gehseeker/libwinpthread-1.dll
gehseeker/bin/coll
gehseeker/bin/coll-linux
gehseeker/bin/coll.exe
gehseeker/bin/hard.exe
gehseeker/scripts/collect.sh
gehseeker/scripts/darwin-collect.sh
gehseeker/scripts/darwin_seekeragg.sh
gehseeker/scripts/seekeragg.sh
gehseeker-0.0.2.dist-info/AUTHORS.rst
gehseeker-0.0.2.dist-info/LICENSE.rst
gehseeker-0.0.2.dist-info/METADATA
gehseeker-0.0.2.dist-info/WHEEL
gehseeker-0.0.2.dist-info/top_level.txt
gehseeker-0.0.2.dist-info/RECORD
